d_data_process/__init__.py
d_data_process/source_databank.py
d_data_process/source_email.py
d_data_process/source_file.py
d_data_process-0.1.5.dist-info/METADATA
d_data_process-0.1.5.dist-info/WHEEL
d_data_process-0.1.5.dist-info/top_level.txt
d_data_process-0.1.5.dist-info/RECORD
