Metadata-Version: 2.1
Name: d-data-process
Version: 0.1.5
Summary: This is a package
Home-page: UNKNOWN
Author: Damon
Author-email: 5178646@qq.com
License: MIT
Platform: UNKNOWN
